{
  "dinos": {
    "321802767_357196693": {
      "id": "321802767_357196693",
      "dinoName": "",
      "species": "Tek Triceratops",
      "dinoClass": "/Game/PrimalEarth/Dinos/Trike/BionicTrike_Character_BP.BionicTrike_Character_BP_C",
      "nameTag": "Trike",
      "isFemale": true,
      "isNeutered": false,
      "level": 328,
      "colors": [
        0,
        0,
        0,
        0,
        0,
        0
      ],
      "colorHex": [
        "#00ffff",
        "#00ffff",
        "#00ffff",
        "#ff00ff",
        "#ff00ff",
        "#ff00ff"
      ],
      "imprint": 0,
      "mutationsMale": 6300,
      "mutationsFemale": 4200,
      "babyAge": 0.0150334388,
      "tamingEffectiveness": 1,
      "isCryopodded": false,
      "tribeName": "",
      "ownerName": "TheDAmOldGamers",
      "imprinterName": "Rhiley",
      "map": "Imported",
      "stats": {
        "health": 7875.06982,
        "stamina": 1065,
        "oxygen": 150,
        "food": 3000,
        "weight": 846.799988,
        "melee": 6.13831997,
        "speed": 1.20000005,
        "fortitude": 0,
        "crafting": 0
      },
      "_source": "ini_import"
    },
    "42427012_451787823": {
      "id": "42427012_451787823",
      "dinoName": "PB",
      "species": "Dunkleosteus",
      "dinoClass": "/Game/PrimalEarth/Dinos/Dunkleosteus/Dunkle_Character_BP.Dunkle_Character_BP_C",
      "nameTag": "Dunkle",
      "isFemale": false,
      "isNeutered": false,
      "level": 373,
      "colors": [
        0,
        0,
        0,
        0,
        0,
        0
      ],
      "colorHex": [
        "#101010",
        "#000000",
        "#000000",
        "#000000",
        "#101010",
        "#ff00ff"
      ],
      "imprint": 0,
      "mutationsMale": 0,
      "mutationsFemale": 0,
      "babyAge": 1,
      "tamingEffectiveness": 1,
      "isCryopodded": false,
      "tribeName": "",
      "ownerName": "TheDAmOldGamers",
      "imprinterName": "Rhiley",
      "map": "Imported",
      "stats": {
        "health": 10366.042,
        "stamina": 1000,
        "oxygen": 150,
        "food": 9890,
        "weight": 3512.59985,
        "melee": 5.51503992,
        "speed": 0,
        "fortitude": 0,
        "crafting": 0
      },
      "_source": "ini_import"
    },
    "336943093_120133039": {
      "id": "336943093_120133039",
      "dinoName": "",
      "species": "Oviraptor",
      "dinoClass": "/Game/PrimalEarth/Dinos/Oviraptor/Oviraptor_Character_BP.Oviraptor_Character_BP_C",
      "nameTag": "Ovi",
      "isFemale": true,
      "isNeutered": false,
      "level": 421,
      "colors": [
        0,
        0,
        0,
        0,
        0,
        0
      ],
      "colorHex": [
        "#00ffff",
        "#00ffff",
        "#00ffff",
        "#00ffff",
        "#00ffff",
        "#00ffff"
      ],
      "imprint": 1,
      "mutationsMale": 0,
      "mutationsFemale": 0,
      "babyAge": 1,
      "tamingEffectiveness": 1,
      "isCryopodded": false,
      "tribeName": "",
      "ownerName": "TheDAmOldGamers",
      "imprinterName": "Rhiley",
      "map": "Imported",
      "stats": {
        "health": 1982.46997,
        "stamina": 972,
        "oxygen": 1065,
        "food": 8694,
        "weight": 362.496002,
        "melee": 8.37591839,
        "speed": 1.29999995,
        "fortitude": 0,
        "crafting": 0
      },
      "_source": "ini_import"
    },
    "400817811_479158473": {
      "id": "400817811_479158473",
      "dinoName": "Nightmare",
      "species": "Maeguana",
      "dinoClass": "/Game/ASA/Dinos/Maelizard/Maelizard_Character_BP.Maelizard_Character_BP_C",
      "nameTag": "Maelizard",
      "isFemale": true,
      "isNeutered": false,
      "level": 427,
      "colors": [
        0,
        0,
        0,
        0,
        0,
        0
      ],
      "colorHex": [
        "#101010",
        "#101010",
        "#8000ff",
        "#101010",
        "#101010",
        "#101010"
      ],
      "imprint": 1,
      "mutationsMale": 0,
      "mutationsFemale": 0,
      "babyAge": 1,
      "tamingEffectiveness": 1,
      "isCryopodded": false,
      "tribeName": "",
      "ownerName": "TheDAmOldGamers",
      "imprinterName": "Rhiley",
      "map": "Imported",
      "stats": {
        "health": 840.000061,
        "stamina": 450,
        "oxygen": 150,
        "food": 575424,
        "weight": 968.447998,
        "melee": 0.117200062,
        "speed": 0,
        "fortitude": 0,
        "crafting": 0
      },
      "_source": "ini_import"
    },
    "438313819_388356586": {
      "id": "438313819_388356586",
      "dinoName": "",
      "species": "Veilwyn",
      "dinoClass": "/Game/LostColony/Dinos/YoungIceFox/YoungIceFox_DinoCompanion_Character_BP.YoungIceFox_DinoCompanion_Character_BP_C",
      "nameTag": "Young Ice Fox",
      "isFemale": true,
      "isNeutered": false,
      "level": 439,
      "colors": [
        0,
        0,
        0,
        0,
        0,
        0
      ],
      "colorHex": [
        "#ff099b",
        "#00ffff",
        "#c9cbcb",
        "#00ffff",
        "#00ffff",
        "#ff099b"
      ],
      "imprint": 1,
      "mutationsMale": 0,
      "mutationsFemale": 0,
      "babyAge": 1,
      "tamingEffectiveness": 1,
      "isCryopodded": false,
      "tribeName": "",
      "ownerName": "TheDAmOldGamers",
      "imprinterName": "Rhiley",
      "map": "Imported",
      "stats": {
        "health": 8857.90039,
        "stamina": 1996.80005,
        "oxygen": 150,
        "food": 1656,
        "weight": 1040.25598,
        "melee": 17.3870792,
        "speed": 0.300000012,
        "fortitude": 0,
        "crafting": 0
      },
      "_source": "ini_import"
    },
    "308917501_439477346": {
      "id": "308917501_439477346",
      "dinoName": "Refrigerator",
      "species": "Ice Wyvern",
      "dinoClass": "/Game/ASA/Dinos/IceWyvern/Wyvern_Character_BP_Ice.Wyvern_Character_BP_Ice_C",
      "nameTag": "Wyvern",
      "isFemale": false,
      "isNeutered": false,
      "level": 420,
      "colors": [
        0,
        0,
        0,
        0,
        0,
        0
      ],
      "colorHex": [
        "#330066",
        "#101010",
        "#101010",
        "#101010",
        "#101010",
        "#101010"
      ],
      "imprint": 0.545454562,
      "mutationsMale": 0,
      "mutationsFemale": 0,
      "babyAge": 1,
      "tamingEffectiveness": 1,
      "isCryopodded": false,
      "tribeName": "",
      "ownerName": "TheDAmOldGamers",
      "imprinterName": "Rhiley",
      "map": "Imported",
      "stats": {
        "health": 20256.3984,
        "stamina": 708.75,
        "oxygen": 150,
        "food": 1996.36365,
        "weight": 3650.94995,
        "melee": 11.0967636,
        "speed": 0,
        "fortitude": 0,
        "crafting": 0
      },
      "_source": "ini_import"
    },
    "51109503_310252551": {
      "id": "51109503_310252551",
      "dinoName": "Stranger Danger",
      "species": "Tek Parasaur",
      "dinoClass": "/Game/PrimalEarth/Dinos/Para/BionicPara_Character_BP.BionicPara_Character_BP_C",
      "nameTag": "Para",
      "isFemale": true,
      "isNeutered": false,
      "level": 450,
      "colors": [
        0,
        0,
        0,
        0,
        0,
        0
      ],
      "colorHex": [
        "#101010",
        "#821c11",
        "#be78bf",
        "#bfffbf",
        "#505050",
        "#e1ffe1"
      ],
      "imprint": 0,
      "mutationsMale": 0,
      "mutationsFemale": 0,
      "babyAge": 1,
      "tamingEffectiveness": 1,
      "isCryopodded": false,
      "tribeName": "",
      "ownerName": "TheDAmOldGamers",
      "imprinterName": "Rhiley",
      "map": "Imported",
      "stats": {
        "health": 3160.07007,
        "stamina": 3645,
        "oxygen": 1260,
        "food": 15000,
        "weight": 1228.80005,
        "melee": 3.90392041,
        "speed": 0.670000017,
        "fortitude": 0,
        "crafting": 0
      },
      "_source": "ini_import"
    },
    "337538811_277144009": {
      "id": "337538811_277144009",
      "dinoName": "PB",
      "species": "Gigantoraptor",
      "dinoClass": "/Game/ASA/Dinos/Gigantoraptor/Gigantoraptor_Character_BP.Gigantoraptor_Character_BP_C",
      "nameTag": "Gigantoraptor",
      "isFemale": true,
      "isNeutered": false,
      "level": 316,
      "colors": [
        0,
        0,
        0,
        0,
        0,
        0
      ],
      "colorHex": [
        "#101010",
        "#ff00ff",
        "#ff00ff",
        "#ff00ff",
        "#ff00ff",
        "#ff00ff"
      ],
      "imprint": 1,
      "mutationsMale": 0,
      "mutationsFemale": 0,
      "babyAge": 1,
      "tamingEffectiveness": 1,
      "isCryopodded": false,
      "tribeName": "",
      "ownerName": "TheDAmOldGamers",
      "imprinterName": "Rhiley",
      "map": "Imported",
      "stats": {
        "health": 19404.0703,
        "stamina": 490,
        "oxygen": 690,
        "food": 4140,
        "weight": 952.320007,
        "melee": 7.62008095,
        "speed": 0,
        "fortitude": 0,
        "crafting": 0
      },
      "_source": "ini_import"
    },
    "441656764_371170653": {
      "id": "441656764_371170653",
      "dinoName": "",
      "species": "Karkinos",
      "dinoClass": "/Game/Aberration/Dinos/Crab/Crab_Character_BP.Crab_Character_BP_C",
      "nameTag": "CaveCrab",
      "isFemale": true,
      "isNeutered": false,
      "level": 163,
      "colors": [
        0,
        0,
        0,
        0,
        0,
        0
      ],
      "colorHex": [
        "#00ffff",
        "#000000",
        "#000000",
        "#ff00ff",
        "#ff00ff",
        "#ffe1bc"
      ],
      "imprint": 0,
      "mutationsMale": 0,
      "mutationsFemale": 0,
      "babyAge": 0.131702319,
      "tamingEffectiveness": 1,
      "isCryopodded": false,
      "tribeName": "",
      "ownerName": "TheDAmOldGamers",
      "imprinterName": "Nixon",
      "map": "Imported",
      "stats": {
        "health": 2640.07007,
        "stamina": 600,
        "oxygen": 150,
        "food": 9000,
        "weight": 3040,
        "melee": 0.72871995,
        "speed": 0,
        "fortitude": 0,
        "crafting": 0
      },
      "_source": "ini_import"
    },
    "7076327_296685251": {
      "id": "7076327_296685251",
      "dinoName": "",
      "species": "Drakeling (Spring)",
      "dinoClass": "/Game/ASA/Dinos/ShoulderDragon/ShoulderDragon_Character_BP_Spring.ShoulderDragon_Character_BP_Spring_C",
      "nameTag": "ShoulderDragon",
      "isFemale": false,
      "isNeutered": false,
      "level": 390,
      "colors": [
        0,
        0,
        0,
        0,
        0,
        0
      ],
      "colorHex": [
        "#101010",
        "#101010",
        "#101010",
        "#101010",
        "#101010",
        "#101010"
      ],
      "imprint": 0,
      "mutationsMale": 0,
      "mutationsFemale": 0,
      "babyAge": 0.685035408,
      "tamingEffectiveness": 1,
      "isCryopodded": false,
      "tribeName": "",
      "ownerName": "TheDAmOldGamers",
      "imprinterName": "Rhiley",
      "map": "Imported",
      "stats": {
        "health": 2940.07007,
        "stamina": 1425,
        "oxygen": 150,
        "food": 3800,
        "weight": 189.799988,
        "melee": 5.37391996,
        "speed": 0,
        "fortitude": 0,
        "crafting": 0
      },
      "_source": "ini_import"
    },
    "188266745_175964329": {
      "id": "188266745_175964329",
      "dinoName": "",
      "species": "Aberrant Otter",
      "dinoClass": "/Game/PrimalEarth/Dinos/Otter/Otter_Character_BP_Aberrant.Otter_Character_BP_Aberrant_C",
      "nameTag": "Otter",
      "isFemale": false,
      "isNeutered": false,
      "level": 362,
      "colors": [
        0,
        0,
        0,
        0,
        0,
        0
      ],
      "colorHex": [
        "#8000ff",
        "#000000",
        "#000000",
        "#000000",
        "#00ff00",
        "#00ff00"
      ],
      "imprint": 0,
      "mutationsMale": 0,
      "mutationsFemale": 0,
      "babyAge": 1,
      "tamingEffectiveness": 1,
      "isCryopodded": false,
      "tribeName": "",
      "ownerName": "TheDAmOldGamers",
      "imprinterName": "Britters",
      "map": "Imported",
      "stats": {
        "health": 384.070007,
        "stamina": 936,
        "oxygen": 600,
        "food": 1880,
        "weight": 123.599991,
        "melee": 4.06855965,
        "speed": 0.699999988,
        "fortitude": 0,
        "crafting": 0
      },
      "_source": "ini_import"
    },
    "352469161_133396240": {
      "id": "352469161_133396240",
      "dinoName": "Rotten Joker",
      "species": "Maeguana",
      "dinoClass": "/Game/ASA/Dinos/Maelizard/Maelizard_Character_BP.Maelizard_Character_BP_C",
      "nameTag": "Maelizard",
      "isFemale": true,
      "isNeutered": false,
      "level": 422,
      "colors": [
        0,
        0,
        0,
        0,
        0,
        0
      ],
      "colorHex": [
        "#101010",
        "#00ff00",
        "#8000ff",
        "#00ff00",
        "#101010",
        "#101010"
      ],
      "imprint": 1,
      "mutationsMale": 0,
      "mutationsFemale": 0,
      "babyAge": 1,
      "tamingEffectiveness": 1,
      "isCryopodded": false,
      "tribeName": "",
      "ownerName": "TheDAmOldGamers",
      "imprinterName": "Rhiley",
      "map": "Imported",
      "stats": {
        "health": 840.000061,
        "stamina": 450,
        "oxygen": 150,
        "food": 544320,
        "weight": 931.200012,
        "melee": 0.117200062,
        "speed": 0,
        "fortitude": 0,
        "crafting": 0
      },
      "_source": "ini_import"
    },
    "121554308_414725177": {
      "id": "121554308_414725177",
      "dinoName": "Maya Jama",
      "species": "Carcharodontosaurus",
      "dinoClass": "/Game/PrimalEarth/Dinos/Carcharodontosaurus/Carcha_Character_BP.Carcha_Character_BP_C",
      "nameTag": "Carcha",
      "isFemale": true,
      "isNeutered": false,
      "level": 348,
      "colors": [
        0,
        0,
        0,
        0,
        0,
        0
      ],
      "colorHex": [
        "#101010",
        "#000000",
        "#101010",
        "#101010",
        "#101010",
        "#101010"
      ],
      "imprint": 1,
      "mutationsMale": 0,
      "mutationsFemale": 0,
      "babyAge": 0.561127245,
      "tamingEffectiveness": 1,
      "isCryopodded": false,
      "tribeName": "",
      "ownerName": "TheDAmOldGamers",
      "imprinterName": "Human",
      "map": "Imported",
      "stats": {
        "health": 34838.4062,
        "stamina": 716.160034,
        "oxygen": 150,
        "food": 4800,
        "weight": 2059.2002,
        "melee": 6.06000042,
        "speed": 0,
        "fortitude": 0,
        "crafting": 0
      },
      "_source": "ini_import"
    },
    "4418378_181804715": {
      "id": "4418378_181804715",
      "dinoName": "",
      "species": "Mantis",
      "dinoClass": "/Game/ScorchedEarth/Dinos/Mantis/Mantis_Character_BP.Mantis_Character_BP_C",
      "nameTag": "Mantis",
      "isFemale": false,
      "isNeutered": false,
      "level": 154,
      "colors": [
        0,
        0,
        0,
        0,
        0,
        0
      ],
      "colorHex": [
        "#101010",
        "#000000",
        "#000000",
        "#000000",
        "#101010",
        "#101010"
      ],
      "imprint": 0.460000008,
      "mutationsMale": 0,
      "mutationsFemale": 0,
      "babyAge": 0.347227395,
      "tamingEffectiveness": 1,
      "isCryopodded": false,
      "tribeName": "",
      "ownerName": "TheDutchOldGamers",
      "imprinterName": "LadyErebus13",
      "map": "Imported",
      "stats": {
        "health": 3363.43018,
        "stamina": 855,
        "oxygen": 150,
        "food": 982.799988,
        "weight": 485.284821,
        "melee": 0.494931191,
        "speed": 0.670000017,
        "fortitude": 0,
        "crafting": 0
      },
      "_source": "ini_import"
    },
    "65373820_29985166": {
      "id": "65373820_29985166",
      "dinoName": "S245 F",
      "species": "Pegomastax",
      "dinoClass": "/Game/PrimalEarth/Dinos/Pegomastax/Pegomastax_Character_BP.Pegomastax_Character_BP_C",
      "nameTag": "Pegomastax",
      "isFemale": true,
      "isNeutered": false,
      "level": 450,
      "colors": [
        0,
        0,
        0,
        0,
        0,
        0
      ],
      "colorHex": [
        "#ffc000",
        "#ffc000",
        "#ffc000",
        "#000000",
        "#ffc000",
        "#ffc000"
      ],
      "imprint": 1,
      "mutationsMale": 0,
      "mutationsFemale": 0,
      "babyAge": 1,
      "tamingEffectiveness": 1,
      "isCryopodded": false,
      "tribeName": "",
      "ownerName": "TheDutchOldGamers",
      "imprinterName": "DViperNL",
      "map": "Imported",
      "stats": {
        "health": 2073.67017,
        "stamina": 810,
        "oxygen": 1215,
        "food": 5030.1001,
        "weight": 324.720032,
        "melee": 5.58560038,
        "speed": 0.5,
        "fortitude": 0,
        "crafting": 0
      },
      "_source": "ini_import"
    },
    "15557603_247102196": {
      "id": "15557603_247102196",
      "dinoName": "",
      "species": "Yutyrannus",
      "dinoClass": "/Game/PrimalEarth/Dinos/Yutyrannus/Yutyrannus_Character_BP.Yutyrannus_Character_BP_C",
      "nameTag": "Yutyrannus",
      "isFemale": true,
      "isNeutered": false,
      "level": 171,
      "colors": [
        0,
        0,
        0,
        0,
        0,
        0
      ],
      "colorHex": [
        "#595959",
        "#8000ff",
        "#000000",
        "#000000",
        "#8000ff",
        "#383838"
      ],
      "imprint": 0,
      "mutationsMale": 0,
      "mutationsFemale": 0,
      "babyAge": 0.65263176,
      "tamingEffectiveness": 1,
      "isCryopodded": false,
      "tribeName": "",
      "ownerName": "TheDutchOldGamers",
      "imprinterName": "Gangstersnorleks",
      "map": "Imported",
      "stats": {
        "health": 25080.0703,
        "stamina": 966,
        "oxygen": 300,
        "food": 3000,
        "weight": 770,
        "melee": 0.905119896,
        "speed": 0,
        "fortitude": 0,
        "crafting": 0
      },
      "_source": "ini_import"
    },
    "225132549_70298006": {
      "id": "225132549_70298006",
      "dinoName": "Deadpool 1 F",
      "species": "Bison",
      "dinoClass": "/Game/ASA/Dinos/Bison/Bison_Character_BP.Bison_Character_BP_C",
      "nameTag": "Bison",
      "isFemale": true,
      "isNeutered": false,
      "level": 1,
      "colors": [
        0,
        0,
        0,
        0,
        0,
        0
      ],
      "colorHex": [
        "#101010",
        "#ff0000",
        "#101010",
        "#101010",
        "#ff0000",
        "#101010"
      ],
      "imprint": 0,
      "mutationsMale": 0,
      "mutationsFemale": 0,
      "babyAge": 1,
      "tamingEffectiveness": 1,
      "isCryopodded": false,
      "tribeName": "",
      "ownerName": "TheDutchOldGamers",
      "imprinterName": "Tosh",
      "map": "Imported",
      "stats": {
        "health": 800.070007,
        "stamina": 500,
        "oxygen": 150,
        "food": 3250,
        "weight": 650,
        "melee": 0.258320004,
        "speed": 1.22599995,
        "fortitude": 0,
        "crafting": 0
      },
      "_source": "ini_import"
    },
    "328495732_89965903": {
      "id": "328495732_89965903",
      "dinoName": "Harley Quinn F",
      "species": "Carcharodontosaurus",
      "dinoClass": "/Game/PrimalEarth/Dinos/Carcharodontosaurus/Carcha_Character_BP.Carcha_Character_BP_C",
      "nameTag": "Carcha",
      "isFemale": true,
      "isNeutered": false,
      "level": 362,
      "colors": [
        0,
        0,
        0,
        0,
        0,
        0
      ],
      "colorHex": [
        "#101010",
        "#000000",
        "#ffffff",
        "#ff0000",
        "#ff0000",
        "#ffffff"
      ],
      "imprint": 1,
      "mutationsMale": 0,
      "mutationsFemale": 0,
      "babyAge": 1,
      "tamingEffectiveness": 1,
      "isCryopodded": false,
      "tribeName": "",
      "ownerName": "TheDutchOldGamers",
      "imprinterName": "DViperNL",
      "map": "Imported",
      "stats": {
        "health": 30000,
        "stamina": 480,
        "oxygen": 150,
        "food": 4800,
        "weight": 1466.40002,
        "melee": 18.420002,
        "speed": 0,
        "fortitude": 0,
        "crafting": 0
      },
      "_source": "ini_import"
    },
    "453096530_33899251": {
      "id": "453096530_33899251",
      "dinoName": "",
      "species": "Desmodus",
      "dinoClass": "/Game/Fjordur/Dinos/Desmodus/Desmodus_Character_BP.Desmodus_Character_BP_C",
      "nameTag": "Desmodus",
      "isFemale": false,
      "isNeutered": false,
      "level": 185,
      "colors": [
        0,
        0,
        0,
        0,
        0,
        0
      ],
      "colorHex": [
        "#ff0000",
        "#e1ffe1",
        "#740045",
        "#41335d",
        "#b80040",
        "#ffffff"
      ],
      "imprint": 0.300000012,
      "mutationsMale": 0,
      "mutationsFemale": 0,
      "babyAge": 1,
      "tamingEffectiveness": 1,
      "isCryopodded": false,
      "tribeName": "",
      "ownerName": "TheDutchOldGamers",
      "imprinterName": "DViperNL",
      "map": "Imported",
      "stats": {
        "health": 2932.30273,
        "stamina": 1394,
        "oxygen": 480,
        "food": 4763.31104,
        "weight": 504.559967,
        "melee": 3.63290024,
        "speed": 0.36500001,
        "fortitude": 0,
        "crafting": 0
      },
      "_source": "ini_import"
    },
    "58483594_452002688": {
      "id": "58483594_452002688",
      "dinoName": "Monster Energy F",
      "species": "Ankylosaurus",
      "dinoClass": "/Game/PrimalEarth/Dinos/Ankylo/Ankylo_Character_BP.Ankylo_Character_BP_C",
      "nameTag": "Anky",
      "isFemale": true,
      "isNeutered": false,
      "level": 388,
      "colors": [
        0,
        0,
        0,
        0,
        0,
        0
      ],
      "colorHex": [
        "#101010",
        "#a9ff42",
        "#101010",
        "#101010",
        "#101010",
        "#101010"
      ],
      "imprint": 1,
      "mutationsMale": 0,
      "mutationsFemale": 0,
      "babyAge": 1,
      "tamingEffectiveness": 1,
      "isCryopodded": false,
      "tribeName": "",
      "ownerName": "TheDutchOldGamers",
      "imprinterName": "DViperNL",
      "map": "Imported",
      "stats": {
        "health": 10151.3135,
        "stamina": 962.5,
        "oxygen": 165,
        "food": 19458,
        "weight": 751.679993,
        "melee": 19.7263889,
        "speed": 0.349999994,
        "fortitude": 0,
        "crafting": 0
      },
      "_source": "ini_import"
    },
    "95546637_458888334": {
      "id": "95546637_458888334",
      "dinoName": "Monster energy F Top",
      "species": "Carcharodontosaurus",
      "dinoClass": "/Game/PrimalEarth/Dinos/Carcharodontosaurus/Carcha_Character_BP.Carcha_Character_BP_C",
      "nameTag": "Carcha",
      "isFemale": true,
      "isNeutered": false,
      "level": 430,
      "colors": [
        0,
        0,
        0,
        0,
        0,
        0
      ],
      "colorHex": [
        "#101010",
        "#000000",
        "#00ff00",
        "#101010",
        "#00ff00",
        "#101010"
      ],
      "imprint": 1,
      "mutationsMale": 0,
      "mutationsFemale": 0,
      "babyAge": 1,
      "tamingEffectiveness": 1,
      "isCryopodded": false,
      "tribeName": "",
      "ownerName": "TheDutchOldGamers",
      "imprinterName": "DViperNL",
      "map": "Imported",
      "stats": {
        "health": 30000,
        "stamina": 720,
        "oxygen": 150,
        "food": 4800,
        "weight": 2262,
        "melee": 21.7492332,
        "speed": 0,
        "fortitude": 0,
        "crafting": 0
      },
      "_source": "ini_import"
    },
    "115253107_141849543": {
      "id": "115253107_141849543",
      "dinoName": "Nightmare F",
      "species": "Bison",
      "dinoClass": "/Game/ASA/Dinos/Bison/Bison_Character_BP.Bison_Character_BP_C",
      "nameTag": "Bison",
      "isFemale": true,
      "isNeutered": false,
      "level": 158,
      "colors": [
        0,
        0,
        0,
        0,
        0,
        0
      ],
      "colorHex": [
        "#5900b3",
        "#101010",
        "#101010",
        "#101010",
        "#101010",
        "#101010"
      ],
      "imprint": 1,
      "mutationsMale": 0,
      "mutationsFemale": 0,
      "babyAge": 1,
      "tamingEffectiveness": 1,
      "isCryopodded": false,
      "tribeName": "",
      "ownerName": "TheDutchOldGamers",
      "imprinterName": "DViperNL",
      "map": "Imported",
      "stats": {
        "health": 5568.06982,
        "stamina": 1450,
        "oxygen": 705,
        "food": 15990.001,
        "weight": 1279.20007,
        "melee": 1.48136032,
        "speed": 1.22599995,
        "fortitude": 0,
        "crafting": 0
      },
      "_source": "ini_import"
    },
    "286098189_263557072": {
      "id": "286098189_263557072",
      "dinoName": "",
      "species": "Aberrant Oviraptor",
      "dinoClass": "/Game/PrimalEarth/Dinos/Oviraptor/Oviraptor_Character_BP_Aberrant.Oviraptor_Character_BP_Aberrant_C",
      "nameTag": "Ovi",
      "isFemale": false,
      "isNeutered": false,
      "level": 450,
      "colors": [
        0,
        0,
        0,
        0,
        0,
        0
      ],
      "colorHex": [
        "#ffc000",
        "#ffc000",
        "#ffc000",
        "#ffc000",
        "#ffc000",
        "#ffc000"
      ],
      "imprint": 0,
      "mutationsMale": 0,
      "mutationsFemale": 0,
      "babyAge": 1,
      "tamingEffectiveness": 1,
      "isCryopodded": false,
      "tribeName": "",
      "ownerName": "TheDutchOldGamers",
      "imprinterName": "Todd Mardde",
      "map": "Imported",
      "stats": {
        "health": 1747.2699,
        "stamina": 888,
        "oxygen": 1230,
        "food": 7452,
        "weight": 246,
        "melee": 8.87722397,
        "speed": 1.29999995,
        "fortitude": 0,
        "crafting": 0
      },
      "_source": "ini_import"
    },
    "405949141_150903661": {
      "id": "405949141_150903661",
      "dinoName": "Solid 180 LW M",
      "species": "Lightning Wyvern",
      "dinoClass": "/Game/ScorchedEarth/Dinos/Wyvern/Wyvern_Character_BP_Lightning.Wyvern_Character_BP_Lightning_C",
      "nameTag": "Wyvern",
      "isFemale": false,
      "isNeutered": false,
      "level": 426,
      "colors": [
        0,
        0,
        0,
        0,
        0,
        0
      ],
      "colorHex": [
        "#73ffff",
        "#73ffff",
        "#73ffff",
        "#73ffff",
        "#73ffff",
        "#73ffff"
      ],
      "imprint": 1,
      "mutationsMale": 0,
      "mutationsFemale": 0,
      "babyAge": 1,
      "tamingEffectiveness": 1,
      "isCryopodded": false,
      "tribeName": "",
      "ownerName": "TheDutchOldGamers",
      "imprinterName": "DViperNL",
      "map": "Imported",
      "stats": {
        "health": 15959.3301,
        "stamina": 1890,
        "oxygen": 150,
        "food": 2160,
        "weight": 1267.20007,
        "melee": 18.7936687,
        "speed": 0,
        "fortitude": 0,
        "crafting": 0
      },
      "_source": "ini_import"
    },
    "443741017_489420071": {
      "id": "443741017_489420071",
      "dinoName": "",
      "species": "Mantis",
      "dinoClass": "/Game/ScorchedEarth/Dinos/Mantis/Mantis_Character_BP.Mantis_Character_BP_C",
      "nameTag": "Mantis",
      "isFemale": false,
      "isNeutered": false,
      "level": 370,
      "colors": [
        0,
        0,
        0,
        0,
        0,
        0
      ],
      "colorHex": [
        "#101010",
        "#000000",
        "#000000",
        "#000000",
        "#ff099b",
        "#101010"
      ],
      "imprint": 0.460000008,
      "mutationsMale": 0,
      "mutationsFemale": 0,
      "babyAge": 0.347537935,
      "tamingEffectiveness": 1,
      "isCryopodded": false,
      "tribeName": "",
      "ownerName": "TheDutchOldGamers",
      "imprinterName": "LadyErebus13",
      "map": "Imported",
      "stats": {
        "health": 3603.67017,
        "stamina": 855,
        "oxygen": 150,
        "food": 982.799988,
        "weight": 485.284821,
        "melee": 7.30114937,
        "speed": 0.670000017,
        "fortitude": 0,
        "crafting": 0
      },
      "_source": "ini_import"
    },
    "489001102_150984478": {
      "id": "489001102_150984478",
      "dinoName": "AB DP F",
      "species": "Aberrant Doedicurus",
      "dinoClass": "/Game/PrimalEarth/Dinos/Doedicurus/Doed_Character_BP_Aberrant.Doed_Character_BP_Aberrant_C",
      "nameTag": "Doed",
      "isFemale": true,
      "isNeutered": false,
      "level": 418,
      "colors": [
        0,
        0,
        0,
        0,
        0,
        0
      ],
      "colorHex": [
        "#101010",
        "#ff0000",
        "#000000",
        "#000000",
        "#ff0000",
        "#ff0000"
      ],
      "imprint": 1,
      "mutationsMale": 0,
      "mutationsFemale": 0,
      "babyAge": 1,
      "tamingEffectiveness": 1,
      "isCryopodded": false,
      "tribeName": "",
      "ownerName": "TheDutchOldGamers",
      "imprinterName": "DViperNL",
      "map": "Imported",
      "stats": {
        "health": 5057.24902,
        "stamina": 420,
        "oxygen": 150,
        "food": 4140,
        "weight": 1329.12,
        "melee": 23.5774612,
        "speed": 0.600000024,
        "fortitude": 0,
        "crafting": 0
      },
      "_source": "ini_import"
    },
    "128738384_9790970": {
      "id": "128738384_9790970",
      "dinoName": "Dust",
      "species": "Gacha",
      "dinoClass": "/Game/Extinction/Dinos/Gacha/Gacha_Character_BP.Gacha_Character_BP_C",
      "nameTag": "Gacha",
      "isFemale": true,
      "isNeutered": false,
      "level": 65,
      "colors": [
        0,
        0,
        0,
        0,
        0,
        0
      ],
      "colorHex": [
        "#ff00ff",
        "#ff00ff",
        "#ff00ff",
        "#ff00ff",
        "#ff00ff",
        "#00ffff"
      ],
      "imprint": 0,
      "mutationsMale": 0,
      "mutationsFemale": 0,
      "babyAge": 1,
      "tamingEffectiveness": 1,
      "isCryopodded": false,
      "tribeName": "",
      "ownerName": "TheDutchOldGamers",
      "imprinterName": "3boood",
      "map": "Imported",
      "stats": {
        "health": 750.070007,
        "stamina": 325,
        "oxygen": 150,
        "food": 3000,
        "weight": 550,
        "melee": 0.258320004,
        "speed": 0,
        "fortitude": 0,
        "crafting": 0.639999986
      },
      "_source": "ini_import"
    },
    "2997470_367789475": {
      "id": "2997470_367789475",
      "dinoName": "Dp Dust M",
      "species": "Gacha",
      "dinoClass": "/Game/Extinction/Dinos/Gacha/Gacha_Character_BP.Gacha_Character_BP_C",
      "nameTag": "Gacha",
      "isFemale": false,
      "isNeutered": false,
      "level": 61,
      "colors": [
        0,
        0,
        0,
        0,
        0,
        0
      ],
      "colorHex": [
        "#101010",
        "#ff0000",
        "#101010",
        "#ff0000",
        "#ff0000",
        "#ff0000"
      ],
      "imprint": 0,
      "mutationsMale": 0,
      "mutationsFemale": 0,
      "babyAge": 1,
      "tamingEffectiveness": 1,
      "isCryopodded": false,
      "tribeName": "",
      "ownerName": "TheDutchOldGamers",
      "imprinterName": "Leyrian",
      "map": "Imported",
      "stats": {
        "health": 750.070007,
        "stamina": 325,
        "oxygen": 150,
        "food": 3000,
        "weight": 550,
        "melee": 0.258320004,
        "speed": 0,
        "fortitude": 0,
        "crafting": 0.599999964
      },
      "_source": "ini_import"
    },
    "310222761_77665001": {
      "id": "310222761_77665001",
      "dinoName": "",
      "species": "Rock Drake",
      "dinoClass": "/Game/Aberration/Dinos/RockDrake/RockDrake_Character_BP.RockDrake_Character_BP_C",
      "nameTag": "RockDrake",
      "isFemale": false,
      "isNeutered": false,
      "level": 362,
      "colors": [
        0,
        0,
        0,
        0,
        0,
        0
      ],
      "colorHex": [
        "#101010",
        "#101010",
        "#00ffff",
        "#00ffff",
        "#8000ff",
        "#8000ff"
      ],
      "imprint": 1,
      "mutationsMale": 0,
      "mutationsFemale": 0,
      "babyAge": 1,
      "tamingEffectiveness": 1,
      "isCryopodded": false,
      "tribeName": "",
      "ownerName": "TheDutchOldGamers",
      "imprinterName": "LadyErebus13",
      "map": "Imported",
      "stats": {
        "health": 11632.8008,
        "stamina": 1552.5,
        "oxygen": 150,
        "food": 2400,
        "weight": 480.000031,
        "melee": 18.462801,
        "speed": 0,
        "fortitude": 0,
        "crafting": 0
      },
      "_source": "ini_import"
    },
    "360608982_79862058": {
      "id": "360608982_79862058",
      "dinoName": "Lady S79 F",
      "species": "Rock Drake",
      "dinoClass": "/Game/Aberration/Dinos/RockDrake/RockDrake_Character_BP.RockDrake_Character_BP_C",
      "nameTag": "RockDrake",
      "isFemale": true,
      "isNeutered": false,
      "level": 251,
      "colors": [
        0,
        0,
        0,
        0,
        0,
        0
      ],
      "colorHex": [
        "#101010",
        "#101010",
        "#101010",
        "#101010",
        "#101010",
        "#101010"
      ],
      "imprint": 1,
      "mutationsMale": 0,
      "mutationsFemale": 0,
      "babyAge": 1,
      "tamingEffectiveness": 1,
      "isCryopodded": false,
      "tribeName": "",
      "ownerName": "TheDutchOldGamers",
      "imprinterName": "LadyErebus13",
      "map": "Imported",
      "stats": {
        "health": 13621.8008,
        "stamina": 1575,
        "oxygen": 435,
        "food": 8880,
        "weight": 499.200012,
        "melee": 6.46760035,
        "speed": 0,
        "fortitude": 0,
        "crafting": 0
      },
      "_source": "ini_import"
    },
    "68276193_448171536": {
      "id": "68276193_448171536",
      "dinoName": "",
      "species": "Desmodus",
      "dinoClass": "/Game/Fjordur/Dinos/Desmodus/Desmodus_Character_BP.Desmodus_Character_BP_C",
      "nameTag": "Desmodus",
      "isFemale": false,
      "isNeutered": false,
      "level": 342,
      "colors": [
        0,
        0,
        0,
        0,
        0,
        0
      ],
      "colorHex": [
        "#101010",
        "#ff0000",
        "#101010",
        "#ff0000",
        "#101010",
        "#ff0000"
      ],
      "imprint": 1,
      "mutationsMale": 0,
      "mutationsFemale": 0,
      "babyAge": 1,
      "tamingEffectiveness": 1,
      "isCryopodded": false,
      "tribeName": "",
      "ownerName": "TheDutchOldGamers",
      "imprinterName": "LadyErebus13",
      "map": "Imported",
      "stats": {
        "health": 6423.37012,
        "stamina": 2375,
        "oxygen": 165,
        "food": 2428.80005,
        "weight": 1058.40002,
        "melee": 7.33784151,
        "speed": 0.36500001,
        "fortitude": 0,
        "crafting": 0
      },
      "_source": "ini_import"
    },
    "79378605_493204028": {
      "id": "79378605_493204028",
      "dinoName": "Lady Kuromi F",
      "species": "Rock Drake",
      "dinoClass": "/Game/Aberration/Dinos/RockDrake/RockDrake_Character_BP.RockDrake_Character_BP_C",
      "nameTag": "RockDrake",
      "isFemale": true,
      "isNeutered": false,
      "level": 362,
      "colors": [
        0,
        0,
        0,
        0,
        0,
        0
      ],
      "colorHex": [
        "#ffffff",
        "#101010",
        "#ffffff",
        "#ff73ff",
        "#101010",
        "#ffffff"
      ],
      "imprint": 1,
      "mutationsMale": 0,
      "mutationsFemale": 0,
      "babyAge": 1,
      "tamingEffectiveness": 1,
      "isCryopodded": false,
      "tribeName": "",
      "ownerName": "TheDutchOldGamers",
      "imprinterName": "LadyErebus13",
      "map": "Imported",
      "stats": {
        "health": 11632.8008,
        "stamina": 1552.5,
        "oxygen": 150,
        "food": 2400,
        "weight": 480.000031,
        "melee": 18.462801,
        "speed": 0,
        "fortitude": 0,
        "crafting": 0
      },
      "_source": "ini_import"
    },
    "228810545_408008847": {
      "id": "228810545_408008847",
      "dinoName": "SubZero Top M",
      "species": "Therizinosaur",
      "dinoClass": "/Game/PrimalEarth/Dinos/Therizinosaurus/Therizino_Character_BP.Therizino_Character_BP_C",
      "nameTag": "Therizinosaurus",
      "isFemale": false,
      "isNeutered": false,
      "level": 362,
      "colors": [
        0,
        0,
        0,
        0,
        0,
        0
      ],
      "colorHex": [
        "#101010",
        "#000000",
        "#0000ff",
        "#000000",
        "#0000ff",
        "#101010"
      ],
      "imprint": 1,
      "mutationsMale": 0,
      "mutationsFemale": 0,
      "babyAge": 1,
      "tamingEffectiveness": 1,
      "isCryopodded": false,
      "tribeName": "",
      "ownerName": "TheDutchOldGamers",
      "imprinterName": "LadyErebus13",
      "map": "Imported",
      "stats": {
        "health": 21088.8711,
        "stamina": 750,
        "oxygen": 150,
        "food": 3600.00024,
        "weight": 438.000031,
        "melee": 18.1335201,
        "speed": 0,
        "fortitude": 0,
        "crafting": 0
      },
      "_source": "ini_import"
    },
    "250312353_239434747": {
      "id": "250312353_239434747",
      "dinoName": "Lady Tron",
      "species": "Rock Drake",
      "dinoClass": "/Game/Aberration/Dinos/RockDrake/RockDrake_Character_BP.RockDrake_Character_BP_C",
      "nameTag": "RockDrake",
      "isFemale": true,
      "isNeutered": false,
      "level": 362,
      "colors": [
        0,
        0,
        0,
        0,
        0,
        0
      ],
      "colorHex": [
        "#101010",
        "#101010",
        "#00ffff",
        "#00ffff",
        "#00ffff",
        "#101010"
      ],
      "imprint": 1,
      "mutationsMale": 0,
      "mutationsFemale": 0,
      "babyAge": 1,
      "tamingEffectiveness": 1,
      "isCryopodded": false,
      "tribeName": "",
      "ownerName": "TheDutchOldGamers",
      "imprinterName": "LadyErebus13",
      "map": "Imported",
      "stats": {
        "health": 11632.8008,
        "stamina": 1552.5,
        "oxygen": 150,
        "food": 2400,
        "weight": 480.000031,
        "melee": 18.462801,
        "speed": 0,
        "fortitude": 0,
        "crafting": 0
      },
      "_source": "ini_import"
    },
    "311178003_331892955": {
      "id": "311178003_331892955",
      "dinoName": "",
      "species": "Therizinosaur",
      "dinoClass": "/Game/PrimalEarth/Dinos/Therizinosaurus/Therizino_Character_BP.Therizino_Character_BP_C",
      "nameTag": "Therizinosaurus",
      "isFemale": false,
      "isNeutered": false,
      "level": 362,
      "colors": [
        0,
        0,
        0,
        0,
        0,
        0
      ],
      "colorHex": [
        "#330066",
        "#000000",
        "#330066",
        "#000000",
        "#330066",
        "#330066"
      ],
      "imprint": 1,
      "mutationsMale": 0,
      "mutationsFemale": 0,
      "babyAge": 1,
      "tamingEffectiveness": 1,
      "isCryopodded": false,
      "tribeName": "",
      "ownerName": "TheDutchOldGamers",
      "imprinterName": "LadyErebus13",
      "map": "Imported",
      "stats": {
        "health": 21088.8711,
        "stamina": 300,
        "oxygen": 150,
        "food": 3600.00024,
        "weight": 438.000031,
        "melee": 19.1919193,
        "speed": 0,
        "fortitude": 0,
        "crafting": 0
      },
      "_source": "ini_import"
    },
    "323932836_379512159": {
      "id": "323932836_379512159",
      "dinoName": "",
      "species": "Therizinosaur",
      "dinoClass": "/Game/PrimalEarth/Dinos/Therizinosaurus/Therizino_Character_BP.Therizino_Character_BP_C",
      "nameTag": "Therizinosaurus",
      "isFemale": true,
      "isNeutered": false,
      "level": 350,
      "colors": [
        0,
        0,
        0,
        0,
        0,
        0
      ],
      "colorHex": [
        "#ffff00",
        "#000000",
        "#ffff00",
        "#000000",
        "#ffff00",
        "#ffff00"
      ],
      "imprint": 1,
      "mutationsMale": 0,
      "mutationsFemale": 0,
      "babyAge": 1,
      "tamingEffectiveness": 1,
      "isCryopodded": false,
      "tribeName": "",
      "ownerName": "TheDutchOldGamers",
      "imprinterName": "Gangstersnorleks",
      "map": "Imported",
      "stats": {
        "health": 21506.4707,
        "stamina": 330,
        "oxygen": 150,
        "food": 3600.00024,
        "weight": 438.000031,
        "melee": 18.1335201,
        "speed": 0,
        "fortitude": 0,
        "crafting": 0
      },
      "_source": "ini_import"
    },
    "386115277_260233228": {
      "id": "386115277_260233228",
      "dinoName": "Batman F",
      "species": "Therizinosaur",
      "dinoClass": "/Game/PrimalEarth/Dinos/Therizinosaurus/Therizino_Character_BP.Therizino_Character_BP_C",
      "nameTag": "Therizinosaurus",
      "isFemale": true,
      "isNeutered": false,
      "level": 229,
      "colors": [
        0,
        0,
        0,
        0,
        0,
        0
      ],
      "colorHex": [
        "#101010",
        "#000000",
        "#ffff00",
        "#000000",
        "#101010",
        "#101010"
      ],
      "imprint": 1,
      "mutationsMale": 0,
      "mutationsFemale": 0,
      "babyAge": 1,
      "tamingEffectiveness": 1,
      "isCryopodded": false,
      "tribeName": "",
      "ownerName": "TheDutchOldGamers",
      "imprinterName": "LadyErebus13",
      "map": "Imported",
      "stats": {
        "health": 2714.47021,
        "stamina": 480,
        "oxygen": 195,
        "food": 6480.00049,
        "weight": 464.279999,
        "melee": 14.6055202,
        "speed": 0,
        "fortitude": 0,
        "crafting": 0
      },
      "_source": "ini_import"
    }
  }
}